smart_detect/__init__.py
smart_detect/main.py
smart_detect/utils.py
smart_detect-0.2.4.dist-info/LICENSE
smart_detect-0.2.4.dist-info/METADATA
smart_detect-0.2.4.dist-info/WHEEL
smart_detect-0.2.4.dist-info/top_level.txt
smart_detect-0.2.4.dist-info/RECORD
