Metadata-Version: 2.1
Name: smart_detect
Version: 0.2.4
Summary: A smart pose detection package for movement analysis using OpenCV and Mediapipe
Home-page: https://github.com/Nandini-0405
Author: Nandini
Author-email: 231031012@juitsolan.in
Classifier: Programming Language :: Python :: 3
Classifier: License :: OSI Approved :: MIT License
Classifier: Operating System :: OS Independent
Requires-Python: >=3.6
License-File: LICENSE
Requires-Dist: opencv-python
Requires-Dist: mediapipe
Requires-Dist: numpy
